LICENSE
MANIFEST.in
README.md
VERSION
gulp_metadata_modifier.py
setup.cfg
setup.py
gulp_metadata_modifier.egg-info/PKG-INFO
gulp_metadata_modifier.egg-info/SOURCES.txt
gulp_metadata_modifier.egg-info/dependency_links.txt
gulp_metadata_modifier.egg-info/entry_points.txt
gulp_metadata_modifier.egg-info/requires.txt
gulp_metadata_modifier.egg-info/top_level.txt