Metadata-Version: 2.1
Name: gulp-metadata-modifier
Version: 0.0.5
Summary: A tool for updating gulp metadata
Home-page: https://github.com/willprice/gulp_metadata_modifier
Author: Will Price
Author-email: will.price94@gmail.com
License: MIT
Platform: UNKNOWN
Classifier: Programming Language :: Python :: 3
Classifier: License :: OSI Approved :: MIT License
Classifier: Operating System :: OS Independent
Requires-Python: >=3.6
